[
  {
    "id": "cv-fresh-tipsy",
    "type": "scheme",
    "name": "便利店清爽微醺方案",
    "enName": "Convenience Fresh Highball",
    "tags": [
      "便利店",
      "清爽",
      "微醺",
      "低酒精",
      "气泡感"
    ],
    "reason": "适合下班路上临时买，小瓶酒加一瓶清爽软饮就能做；气泡水、汤力水、雪碧都可以按口味替换。",
    "flavor": {
      "sweet": 1,
      "sour": 2,
      "alcohol": 2,
      "fresh": 5,
      "difficulty": 1
    },
    "place": [
      "便利店",
      "宿舍/租房",
      "聚会前临时采购"
    ],
    "mood": [
      "清爽",
      "微醺",
      "低酒精",
      "气泡感"
    ],
    "price": "约 35-55 元",
    "materials": {
      "standard": [
        "金酒小瓶",
        "汤力水 / 气泡水 / 雪碧",
        "冰杯",
        "柠檬片可选"
      ],
      "convenience": [
        "金酒小瓶 1支",
        "喜欢的清爽软饮 1瓶",
        "冰杯 1杯",
        "柠檬片可选"
      ],
      "simple": [
        "金酒",
        "喜欢的饮料",
        "冰块"
      ]
    },
    "steps": [
      "冰杯倒入金酒 25-35ml。",
      "补汤力水、气泡水、雪碧或喜欢的茶饮。",
      "有柠檬再挤一点，没有就直接轻搅。"
    ],
    "scenes": [
      "下班放松",
      "夏天晚上",
      "一个人微醺",
      "不想喝甜"
    ],
    "substitutes": [
      "没有汤力水就用气泡水、雪碧或无糖茶。",
      "不喜欢气泡水就换茶饮或果汁。",
      "柠檬和薄荷买不到都可以不加。"
    ],
    "warnings": [
      "便利店冰杯融化快，先冰饮料再混合。"
    ],
    "similar": [
      "gin-tonic",
      "tom-collins",
      "whisky-highball"
    ]
  },
  {
    "id": "cv-sweet-party",
    "type": "scheme",
    "name": "便利店甜口聚会方案",
    "enName": "Convenience Sweet Party",
    "tags": [
      "便利店",
      "甜口",
      "聚会",
      "低门槛",
      "气泡感"
    ],
    "reason": "适合朋友小聚，材料好买，几乎不需要调酒工具。",
    "flavor": {
      "sweet": 4,
      "sour": 1,
      "alcohol": 3,
      "fresh": 3,
      "difficulty": 1
    },
    "place": [
      "便利店",
      "超市",
      "聚会前临时采购"
    ],
    "mood": [
      "甜口",
      "果味",
      "微醺"
    ],
    "price": "约 45-80 元",
    "materials": {
      "standard": [
        "威士忌或朗姆",
        "可乐",
        "冰块",
        "柠檬可选"
      ],
      "convenience": [
        "威士忌小瓶或朗姆小瓶 1支",
        "可乐 1瓶",
        "冰杯 2杯",
        "柠檬片可选"
      ],
      "simple": [
        "威士忌",
        "可乐"
      ]
    },
    "steps": [
      "冰杯加威士忌或朗姆 30-45ml。",
      "补可乐。",
      "有柠檬再加一点减少甜腻，没有就直接做。"
    ],
    "scenes": [
      "朋友小聚",
      "聚会前临时采购",
      "甜口入门",
      "不想失败"
    ],
    "substitutes": [
      "威士忌可换朗姆。",
      "怕甜用无糖可乐或加一点气泡水。",
      "想增加风味可换樱桃可乐、柠檬茶或果汁。"
    ],
    "warnings": [
      "可乐很遮酒味，别连续加太多基酒。"
    ],
    "similar": [
      "whisky-cola",
      "cuba-libre",
      "jager-cola"
    ]
  },
  {
    "id": "cv-milk-soft",
    "type": "scheme",
    "name": "便利店奶香低门槛方案",
    "enName": "Convenience Creamy Soft",
    "tags": [
      "便利店",
      "奶香",
      "甜口",
      "新手友好",
      "低门槛"
    ],
    "reason": "适合不喜欢明显酒味的人，像一杯带酒感的甜品饮料。",
    "flavor": {
      "sweet": 5,
      "sour": 0,
      "alcohol": 1,
      "fresh": 2,
      "difficulty": 1
    },
    "place": [
      "便利店",
      "家里",
      "宿舍/租房"
    ],
    "mood": [
      "奶香",
      "甜口",
      "低酒精"
    ],
    "price": "约 30-60 元",
    "materials": {
      "standard": [
        "百利甜",
        "牛奶",
        "冰块"
      ],
      "convenience": [
        "百利甜小瓶",
        "鲜牛奶或冰牛奶",
        "冰杯"
      ],
      "simple": [
        "百利甜",
        "牛奶"
      ]
    },
    "steps": [
      "冰杯倒入百利甜。",
      "补牛奶。",
      "搅匀后试甜度。"
    ],
    "scenes": [
      "饭后甜口",
      "宿舍/租房",
      "女生更容易接受",
      "低酒精"
    ],
    "substitutes": [
      "牛奶可换咖啡。",
      "怕甜就增加牛奶比例。",
      "想更冰爽就多加冰。"
    ],
    "warnings": [
      "不要和高酸果汁混合。"
    ],
    "similar": [
      "baileys-milk",
      "baileys-coffee"
    ]
  },
  {
    "id": "cv-tea-light",
    "type": "scheme",
    "name": "便利店茶感不甜方案",
    "enName": "Convenience Tea Light",
    "tags": [
      "便利店",
      "茶感",
      "不太甜",
      "清爽",
      "新手友好"
    ],
    "reason": "适合不想喝甜饮，又想要一点微醺和茶香的人。",
    "flavor": {
      "sweet": 1,
      "sour": 0,
      "alcohol": 2,
      "fresh": 4,
      "difficulty": 1
    },
    "place": [
      "便利店",
      "宿舍/租房",
      "家里"
    ],
    "mood": [
      "茶感",
      "清爽",
      "微醺",
      "低酒精"
    ],
    "price": "约 30-55 元",
    "materials": {
      "standard": [
        "威士忌或伏特加",
        "无糖乌龙茶",
        "冰块"
      ],
      "convenience": [
        "威士忌小瓶或伏特加小瓶",
        "无糖乌龙茶 1瓶",
        "冰杯 1杯"
      ],
      "simple": [
        "基酒",
        "茶",
        "冰块"
      ]
    },
    "steps": [
      "冰杯倒入基酒 25-35ml。",
      "补无糖乌龙茶。",
      "搅匀后按酒感加茶调整。"
    ],
    "scenes": [
      "下班放松",
      "宿舍/租房",
      "不想喝太甜",
      "便利店调酒"
    ],
    "substitutes": [
      "威士忌更有香气，伏特加更干净。",
      "想甜一点换柠檬茶。",
      "想低酒精就只倒半瓶小酒。"
    ],
    "warnings": [
      "茶饮越浓越显酒感，新手建议先少倒酒。"
    ],
    "similar": [
      "whisky-oolong",
      "sake-green-tea",
      "umeshu-oolong"
    ]
  },
  {
    "id": "cv-fruit-low",
    "type": "scheme",
    "name": "便利店果味低酒精方案",
    "enName": "Convenience Fruit Low ABV",
    "tags": [
      "便利店",
      "果味",
      "低酒精",
      "女生更容易接受",
      "酸甜"
    ],
    "reason": "适合想要果汁感、轻微微醺、不想被酒味压住的人。",
    "flavor": {
      "sweet": 3,
      "sour": 2,
      "alcohol": 1,
      "fresh": 4,
      "difficulty": 1
    },
    "place": [
      "便利店",
      "超市",
      "宿舍/租房",
      "聚会前临时采购"
    ],
    "mood": [
      "果味",
      "酸甜",
      "低酒精",
      "微醺"
    ],
    "price": "约 35-65 元",
    "materials": {
      "standard": [
        "伏特加或低度果酒",
        "橙汁 / 葡萄柚汁 / 茶饮",
        "冰块",
        "气泡水可选"
      ],
      "convenience": [
        "伏特加小瓶或果酒",
        "喜欢的果汁或茶饮 1瓶",
        "冰杯",
        "气泡水可选"
      ],
      "simple": [
        "伏特加",
        "果汁或茶饮",
        "冰块"
      ]
    },
    "steps": [
      "冰杯倒入少量基酒。",
      "加入果汁或茶饮至七八分满。",
      "喜欢更轻盈再补一点气泡水，不喜欢就省略。"
    ],
    "scenes": [
      "新手第一杯",
      "女生更容易接受",
      "夏天晚上",
      "朋友小聚"
    ],
    "substitutes": [
      "橙汁更甜，葡萄柚更清爽。",
      "不喜欢气泡水就全用果汁或茶饮。",
      "没有水果辅料也不影响。"
    ],
    "warnings": [
      "果汁遮酒味，聚会时别连续加酒。"
    ],
    "similar": [
      "vodka-orange",
      "sea-breeze",
      "fruit-wine-spritz"
    ]
  },
  {
    "id": "cv-coffee-night",
    "type": "scheme",
    "name": "便利店咖啡夜晚方案",
    "enName": "Convenience Coffee Night",
    "tags": [
      "便利店",
      "咖啡感",
      "苦甜",
      "夜晚",
      "进阶"
    ],
    "reason": "适合咖啡爱好者，做成甜品感或清爽苦甜都可以。",
    "flavor": {
      "sweet": 3,
      "sour": 0,
      "alcohol": 2,
      "fresh": 2,
      "difficulty": 2
    },
    "place": [
      "便利店",
      "家里",
      "宿舍/租房"
    ],
    "mood": [
      "咖啡感",
      "苦甜",
      "奶香",
      "微醺"
    ],
    "price": "约 35-70 元",
    "materials": {
      "standard": [
        "百利甜或伏特加",
        "冷萃咖啡",
        "牛奶可选",
        "冰块"
      ],
      "convenience": [
        "百利甜小瓶或伏特加小瓶",
        "冷萃咖啡",
        "冰杯",
        "牛奶可选"
      ],
      "simple": [
        "百利甜",
        "咖啡"
      ]
    },
    "steps": [
      "冰杯倒入百利甜或伏特加。",
      "补冷萃咖啡。",
      "想柔和就加牛奶。"
    ],
    "scenes": [
      "饭后甜口",
      "咖啡爱好者",
      "夜晚聚会",
      "宿舍/租房"
    ],
    "substitutes": [
      "百利甜走奶香甜口，伏特加走苦甜酒吧感。",
      "怕苦就加牛奶。",
      "想无酒精就做咖啡汤力。"
    ],
    "warnings": [
      "咖啡因会影响睡眠，晚上不要做太大杯。"
    ],
    "similar": [
      "baileys-coffee",
      "espresso-martini",
      "coffee-tonic"
    ]
  },
  {
    "id": "cv-nonalcohol-fresh",
    "type": "scheme",
    "name": "便利店无酒精清爽方案",
    "enName": "Convenience Zero Proof Fresh",
    "tags": [
      "便利店",
      "无酒精",
      "清爽",
      "低门槛",
      "气泡感"
    ],
    "reason": "适合不喝酒但想有“调饮感”的场景，重点是冰杯和喜欢的饮料，柠檬只是让味道更亮。",
    "flavor": {
      "sweet": 1,
      "sour": 2,
      "alcohol": 0,
      "fresh": 5,
      "difficulty": 1
    },
    "place": [
      "便利店",
      "超市",
      "家里",
      "宿舍/租房",
      "聚会前临时采购"
    ],
    "mood": [
      "无酒精",
      "清爽",
      "酸甜",
      "气泡感"
    ],
    "price": "约 15-35 元",
    "materials": {
      "standard": [
        "气泡水 / 雪碧 / 茶饮",
        "无糖茶或冷萃咖啡",
        "冰块",
        "柠檬可选"
      ],
      "convenience": [
        "喜欢的饮料 1瓶",
        "冰杯 1杯",
        "无糖茶或冷萃咖啡",
        "柠檬片可选"
      ],
      "simple": [
        "喜欢的饮料",
        "冰块"
      ]
    },
    "steps": [
      "冰杯倒入喜欢的气泡饮、茶饮或雪碧。",
      "想要层次可加少量茶或咖啡。",
      "有柠檬再加一点，没有就省略。"
    ],
    "scenes": [
      "无酒精",
      "聚会照顾款",
      "下午",
      "不想喝甜"
    ],
    "substitutes": [
      "想甜口用雪碧。",
      "想咖啡感用冷萃加汤力水。",
      "不想气泡就用茶饮或果汁。"
    ],
    "warnings": [
      "无酒精方案也要注意含糖饮料和咖啡因。"
    ],
    "similar": [
      "coffee-tonic",
      "fruit-wine-spritz"
    ]
  },
  {
    "id": "supermarket-party",
    "type": "scheme",
    "name": "超市聚会批量方案",
    "enName": "Supermarket Party Batch",
    "tags": [
      "超市",
      "聚会",
      "果味",
      "甜口",
      "低酒精"
    ],
    "reason": "适合人数多、要快速出杯，用果酒和水果做低风险批量方案。",
    "flavor": {
      "sweet": 3,
      "sour": 2,
      "alcohol": 2,
      "fresh": 4,
      "difficulty": 2
    },
    "place": [
      "超市",
      "聚会前临时采购",
      "家里"
    ],
    "mood": [
      "果味",
      "甜口",
      "低酒精",
      "微醺"
    ],
    "price": "约 80-160 元",
    "materials": {
      "standard": [
        "果酒或低度红酒",
        "气泡水",
        "橙汁",
        "水果",
        "冰块"
      ],
      "convenience": [
        "果酒 1瓶",
        "气泡水 2瓶",
        "水果盒 1份",
        "冰袋"
      ],
      "simple": [
        "果酒",
        "气泡水",
        "水果"
      ]
    },
    "steps": [
      "大壶里加入水果和冰。",
      "倒入果酒。",
      "饮用前补气泡水。",
      "每杯可按口味加橙汁。"
    ],
    "scenes": [
      "朋友小聚",
      "聚会前临时采购",
      "低酒精",
      "甜口入门"
    ],
    "substitutes": [
      "没有果酒可用低度红酒。",
      "想更清爽减少橙汁。",
      "有人不喝酒就单独准备气泡水果杯。"
    ],
    "warnings": [
      "批量调酒容易喝太快，建议做低酒精比例。"
    ],
    "similar": [
      "sangria-light",
      "fruit-wine-spritz",
      "mimosa"
    ]
  }
]